Metadata-Version: 2.1
Name: drfpasswordless-gstr169
Version: 1.1.3
Summary: Passwordless auth for Django Rest Framework Token Authentication. Update by Dmitry F.
Home-page: https://github.com/gstr169/drf-passwordless/
Author: Original: Aaron N. Updated by: Dmitry F.
Author-email: necronomicum169@gmail.com
License: MIT
Classifier: License :: OSI Approved :: MIT License
Classifier: Programming Language :: Python
Classifier: Programming Language :: Python :: 3
Classifier: Programming Language :: Python :: 3.6
Classifier: Programming Language :: Python :: Implementation :: CPython
Classifier: Programming Language :: Python :: Implementation :: PyPy
Classifier: Development Status :: 5 - Production/Stable
Classifier: Environment :: Web Environment
Classifier: Framework :: Django
Classifier: Intended Audience :: Developers
Classifier: Operating System :: OS Independent
Classifier: Programming Language :: Python
Classifier: Topic :: Internet :: WWW/HTTP
Requires-Python: >=3
License-File: LICENSE
Requires-Dist: Django
Requires-Dist: djangorestframework
